main.py
jker_mcp_demo-0.1.0.dist-info/METADATA
jker_mcp_demo-0.1.0.dist-info/WHEEL
jker_mcp_demo-0.1.0.dist-info/top_level.txt
jker_mcp_demo-0.1.0.dist-info/RECORD
