Metadata-Version: 2.4
Name: jker-mcp-demo
Version: 0.1.0
Summary: Add your description here
Requires-Python: >=3.13.5
Requires-Dist: mcp[cli]>=1.13.0
